kash/__init__.py
kash/py.typed
kash/kits/__init__.py
kash/kits/media/__init__.py
kash/kits/media/__main__.py
kash/kits/media/actions/__init__.py
kash/kits/media/actions/transcribe/__init__.py
kash/kits/media/actions/transcribe/backfill_timestamps.py
kash/kits/media/actions/transcribe/identify_speakers.py
kash/kits/media/actions/transcribe/insert_frame_captures.py
kash/kits/media/actions/transcribe/list_channel.py
kash/kits/media/actions/transcribe/remove_speaker_labels.py
kash/kits/media/actions/transcribe/transcribe.py
kash/kits/media/actions/transcribe/transcribe_annotate.py
kash/kits/media/actions/transcribe/transcribe_format.py
kash/kits/media/media_services/__init__.py
kash/kits/media/media_services/apple_podcasts.py
kash/kits/media/media_services/vimeo.py
kash/kits/media/media_services/youtube.py
kash/kits/media/utils/__init__.py
kash/kits/media/utils/yt_dlp_tools.py
kash/kits/media/video/image_similarity.py
kash/kits/media/video/speaker_labels.py
kash/kits/media/video/video_frames.py
kash/kits/media/video/video_gallery.py
kash/kits/media/video/video_preconditions.py
kash/kits/media/video/templates/youtube_gallery.html.jinja
kash_media-0.3.17.dist-info/METADATA
kash_media-0.3.17.dist-info/WHEEL
kash_media-0.3.17.dist-info/entry_points.txt
kash_media-0.3.17.dist-info/licenses/LICENSE
kash_media-0.3.17.dist-info/RECORD
