Metadata-Version: 2.4
Name: kash-media
Version: 0.3.17
Summary: The knowledge agent shell (media kit)
Project-URL: Repository, https://github.com/jlevy/kash-media
Author-email: Joshua Levy <joshua@cal.berkeley.edu>
License-Expression: AGPL-3.0-or-later
License-File: LICENSE
Classifier: Development Status :: 4 - Beta
Classifier: Intended Audience :: Developers
Classifier: Operating System :: OS Independent
Classifier: Programming Language :: Python
Classifier: Programming Language :: Python :: 3
Classifier: Programming Language :: Python :: 3.11
Classifier: Programming Language :: Python :: 3.12
Classifier: Programming Language :: Python :: 3.13
Classifier: Typing :: Typed
Requires-Python: <4.0,>=3.11
Requires-Dist: chopdiff>=0.2.1
Requires-Dist: curl-cffi>=0.7.4
Requires-Dist: flowmark>=0.4.5
Requires-Dist: kash-docs[full]==0.1.19
Requires-Dist: opencv-python>=4.11.0.86
Requires-Dist: scikit-image>=0.25.2
Requires-Dist: sidematter-format>=0.0.3
Requires-Dist: typing-extensions>=4.11.1
Requires-Dist: yt-dlp>=2025.3.27
